MANIFEST.in
setup.cfg
setup.py
JazzminTM/__init__.py
JazzminTM/apps.py
JazzminTM/compat.py
JazzminTM/settings.py
JazzminTM/utils.py
JazzminTM/widgets.py
JazzminTM.egg-info/PKG-INFO
JazzminTM.egg-info/SOURCES.txt
JazzminTM.egg-info/dependency_links.txt
JazzminTM.egg-info/requires.txt
JazzminTM.egg-info/top_level.txt
JazzminTM/locale/.DS_Store
JazzminTM/locale/bg/LC_MESSAGES/django.mo
JazzminTM/locale/bg/LC_MESSAGES/django.po
JazzminTM/locale/de/LC_MESSAGES/django.mo
JazzminTM/locale/de/LC_MESSAGES/django.po
JazzminTM/locale/es/LC_MESSAGES/django.mo
JazzminTM/locale/es/LC_MESSAGES/django.po
JazzminTM/locale/fr/LC_MESSAGES/django.mo
JazzminTM/locale/fr/LC_MESSAGES/django.po
JazzminTM/locale/hu/LC_MESSAGES/django.mo
JazzminTM/locale/hu/LC_MESSAGES/django.po
JazzminTM/locale/ru/LC_MESSAGES/django.mo
JazzminTM/locale/ru/LC_MESSAGES/django.po
JazzminTM/locale/tk/.DS_Store
JazzminTM/locale/tk/LC_MESSAGES/.DS_Store
JazzminTM/locale/tk/LC_MESSAGES/django.mo
JazzminTM/locale/tk/LC_MESSAGES/django.po
JazzminTM/locale/zh_Hans/LC_MESSAGES/django.mo
JazzminTM/locale/zh_Hans/LC_MESSAGES/django.po
JazzminTM/locale/zh_Hant/LC_MESSAGES/django.mo
JazzminTM/locale/zh_Hant/LC_MESSAGES/django.po
JazzminTM/static/admin/js/cancel.js
JazzminTM/static/admin/js/popup_response.js
JazzminTM/static/jazzmin/css/main.css
JazzminTM/static/jazzmin/img/calendar-icons.svg
JazzminTM/static/jazzmin/img/default-log.svg
JazzminTM/static/jazzmin/img/default.jpg
JazzminTM/static/jazzmin/img/icon-calendar.svg
JazzminTM/static/jazzmin/img/icon-changelink.svg
JazzminTM/static/jazzmin/img/selector-icons.svg
JazzminTM/static/jazzmin/js/change_form.js
JazzminTM/static/jazzmin/js/change_list.js
JazzminTM/static/jazzmin/js/main.js
JazzminTM/static/jazzmin/js/related-modal.js
JazzminTM/static/jazzmin/js/ui-builder.js
JazzminTM/static/jazzmin/plugins/bootstrap-show-modal/bootstrap-show-modal.min.js
JazzminTM/static/vendor/adminlte/css/adminlte.min.css
JazzminTM/static/vendor/adminlte/css/adminlte.min.css.map
JazzminTM/static/vendor/adminlte/img/AdminLTELogo.png
JazzminTM/static/vendor/adminlte/img/icons.png
JazzminTM/static/vendor/adminlte/img/user2-160x160.jpg
